Metadata-Version: 2.1
Name: filemanip
Version: 0.0.0
Summary: a simple module to manipulate files, find and remove/replace flags, etc...
Home-page: https://github.com/deadlift1226/filemanip
Author: Dane Morgan
Author-email: danemorgan91@gmail.com
License: UNKNOWN
Platform: UNKNOWN
Classifier: Programming Language :: Python :: 3
Classifier: License :: OSI Approved :: MIT License
Classifier: Operating System :: OS Independent
